cryptfile/__init__.py
cryptfile-1.0.4.dist-info/LICENSE
cryptfile-1.0.4.dist-info/METADATA
cryptfile-1.0.4.dist-info/WHEEL
cryptfile-1.0.4.dist-info/top_level.txt
cryptfile-1.0.4.dist-info/RECORD
