Metadata-Version: 2.1
Name: cryptfile
Version: 1.0.4
Summary: General purpose Python encrypted file-like object with random IO.
Home-page: https://github.com/alemigo/cryptfile
Author: github.com/alemigo
License: UNKNOWN
Platform: UNKNOWN
Classifier: Programming Language :: Python :: 3
Classifier: License :: OSI Approved :: GNU General Public License v3 (GPLv3)
Classifier: Operating System :: OS Independent
Requires-Dist: pycryptodome
